codablellm/__init__.py
codablellm/__main__.py
codablellm/cli.py
codablellm/dataset.py
codablellm/exceptions.py
codablellm/logging_config.py
codablellm/repoman.py
codablellm/core/__init__.py
codablellm/core/decompiler.py
codablellm/core/downloader.py
codablellm/core/extractor.py
codablellm/core/function.py
codablellm/core/mapper.py
codablellm/core/utils.py
codablellm/decompilers/__init__.py
codablellm/decompilers/angr_decompiler.py
codablellm/decompilers/ghidra.py
codablellm/decompilers/radare2.py
codablellm/languages/__init__.py
codablellm/languages/c.py
codablellm/languages/common.py
codablellm/languages/cpp.py
codablellm/languages/java.py
codablellm/languages/javascript.py
codablellm/languages/python_language.py
codablellm/languages/rust.py
codablellm/languages/typescript.py
codablellm/resources/ghidra_scripts/decompile.py
codablellm-1.3.2.dist-info/licenses/LICENSE
codablellm-1.3.2.dist-info/METADATA
codablellm-1.3.2.dist-info/WHEEL
codablellm-1.3.2.dist-info/entry_points.txt
codablellm-1.3.2.dist-info/top_level.txt
codablellm-1.3.2.dist-info/RECORD
