Metadata-Version: 2.4
Name: codablellm
Version: 1.3.2
Summary: A framework for creating and curating high-quality code datasets tailored for large language models
Author-email: Dylan Manuel <dylan.manuel@my.utsa.edu>
Project-URL: Homepage, https://codablellm.readthedocs.io
Project-URL: Bug Tracker, https://github.com/dmanuel64/codablellm/issues
Project-URL: Documentation, https://codablellm.readthedocs.io
Project-URL: GitHub, https://github.com/dmanuel64/codablellm
Keywords: large language models,automation,reverse engineering,software security,dataset generation
Classifier: Development Status :: 4 - Beta
Classifier: Intended Audience :: Developers
Classifier: Topic :: Software Development :: Build Tools
Classifier: Topic :: Software Development :: Code Generators
Classifier: Topic :: Software Development :: Pre-processors
Classifier: Topic :: Software Development :: Version Control
Classifier: Topic :: Security
Classifier: Topic :: Scientific/Engineering :: Artificial Intelligence
Classifier: License :: OSI Approved :: MIT License
Classifier: Operating System :: OS Independent
Classifier: Programming Language :: Python
Classifier: Programming Language :: Python :: 3
Classifier: Programming Language :: Python :: 3.8
Classifier: Programming Language :: Python :: 3.9
Classifier: Programming Language :: Python :: 3.10
Classifier: Programming Language :: Python :: 3.11
Classifier: Programming Language :: Python :: 3.12
Requires-Python: <3.13,>=3.9
License-File: LICENSE
Requires-Dist: Deprecated>=1.2.18
Requires-Dist: GitPython>=3.1.43
Requires-Dist: jinja2>=3.1.6
Requires-Dist: pandas>=2.2.3
Requires-Dist: prefect[dask]>=3.2.15
Requires-Dist: requests>=2.32.3
Requires-Dist: tree-sitter==0.23.2
Requires-Dist: tree-sitter-c==0.23.4
Requires-Dist: tree-sitter-cpp==0.23.4
Requires-Dist: typer>=0.15.1
Provides-Extra: rust
Requires-Dist: tree-sitter-rust==0.23.2; extra == "rust"
Provides-Extra: javascript
Requires-Dist: tree-sitter-javascript==0.23.1; extra == "javascript"
Provides-Extra: typescript
Requires-Dist: tree-sitter-typescript==0.23.2; extra == "typescript"
Provides-Extra: python
Requires-Dist: tree-sitter-python==0.23.6; extra == "python"
Provides-Extra: java
Requires-Dist: tree-sitter-java==0.23.5; extra == "java"
Provides-Extra: langs
Requires-Dist: tree-sitter-rust==0.23.2; extra == "langs"
Requires-Dist: tree-sitter-javascript==0.23.1; extra == "langs"
Requires-Dist: tree-sitter-typescript==0.23.2; extra == "langs"
Requires-Dist: tree-sitter-python==0.23.6; extra == "langs"
Requires-Dist: tree-sitter-java==0.23.5; extra == "langs"
Provides-Extra: angr
Requires-Dist: angr>=9.2.148; extra == "angr"
Provides-Extra: radare2
Requires-Dist: r2pipe>=1.9.4; extra == "radare2"
Provides-Extra: excel
Requires-Dist: openpyxl>=3.1.5; extra == "excel"
Provides-Extra: markdown
Requires-Dist: tabulate>=0.9.0; extra == "markdown"
Provides-Extra: xml
Requires-Dist: lxml>=5.3.0; extra == "xml"
Provides-Extra: all
Requires-Dist: openpyxl>=3.1.5; extra == "all"
Requires-Dist: tabulate>=0.9.0; extra == "all"
Requires-Dist: lxml>=5.3.0; extra == "all"
Requires-Dist: angr>=9.2.148; extra == "all"
Requires-Dist: r2pipe>=1.9.4; extra == "all"
Requires-Dist: tree-sitter-rust==0.23.2; extra == "all"
Requires-Dist: tree-sitter-javascript==0.23.1; extra == "all"
Requires-Dist: tree-sitter-typescript==0.23.2; extra == "all"
Requires-Dist: tree-sitter-python==0.23.6; extra == "all"
Requires-Dist: tree-sitter-java==0.23.5; extra == "all"
Provides-Extra: dev
Requires-Dist: pytest>=8.3.4; extra == "dev"
Provides-Extra: docs
Requires-Dist: mkdocs>=1.6.1; extra == "docs"
Requires-Dist: mkdocs-gen-files>=0.5.0; extra == "docs"
Requires-Dist: mkdocs-literate-nav>=0.6.1; extra == "docs"
Requires-Dist: mkdocs-material>=9.6.5; extra == "docs"
Requires-Dist: mkdocs-section-index>=0.3.9; extra == "docs"
Requires-Dist: mkdocstrings[python]>=0.26.0; extra == "docs"
Dynamic: license-file
